textgraph/__init__.py
textgraph/horizontal.py
textgraph/spark.py
textgraph/util.py
textgraph/vertical.py
textgraph-2.0.0.dist-info/LICENCE
textgraph-2.0.0.dist-info/METADATA
textgraph-2.0.0.dist-info/WHEEL
textgraph-2.0.0.dist-info/top_level.txt
textgraph-2.0.0.dist-info/RECORD
