Metadata-Version: 2.1
Name: textgraph
Version: 2.0.0
Summary: Library for creating text based graphs
Home-page: https://github.com/markeganfuller/pytextgraph
Author: Mark Egan-Fuller
Author-email: markeganfuller@googlemail.com
License: GPLv3+
Keywords: text graph textgraph asciigraph
Platform: UNKNOWN
Classifier: Programming Language :: Python :: 3 :: Only
Classifier: Intended Audience :: Developers
Classifier: License :: OSI Approved :: GNU General Public License v3 or later (GPLv3+)
Classifier: Operating System :: OS Independent
